shining_brain/__init__.py
shining_brain/config_loader.py
shining_brain/constants.py
shining_brain/database.py
shining_brain/etl.py
shining_brain/label_canvas.py
shining_brain/logger_setup.py
shining_brain/str_util.py
shining_brain/util.py
shining_brain-0.21.dist-info/LICENSE
shining_brain-0.21.dist-info/METADATA
shining_brain-0.21.dist-info/WHEEL
shining_brain-0.21.dist-info/top_level.txt
shining_brain-0.21.dist-info/RECORD
