Metadata-Version: 2.1
Name: shining-brain
Version: 0.21
Author: Evan Knox Thomas
Author-email: evanknoxthomas@gmail.com
License-File: LICENSE
Requires-Dist: pandas
Requires-Dist: sqlalchemy
Requires-Dist: PyYAML
Requires-Dist: openpyxl
Requires-Dist: mysql-connector-python
Requires-Dist: pathlib
